axelerate/__init__.py
axelerate/evaluate.py
axelerate/infer.py
axelerate/train.py
axelerate/networks/__init__.py
axelerate/networks/classifier/__init__.py
axelerate/networks/classifier/batch_gen.py
axelerate/networks/classifier/directory_iterator.py
axelerate/networks/classifier/frontend_classifier.py
axelerate/networks/classifier/iterator.py
axelerate/networks/classifier/utils.py
axelerate/networks/common_utils/__init__.py
axelerate/networks/common_utils/augment.py
axelerate/networks/common_utils/callbacks.py
axelerate/networks/common_utils/convert.py
axelerate/networks/common_utils/feature.py
axelerate/networks/common_utils/fit.py
axelerate/networks/common_utils/mobilenet_sipeed/__init__.py
axelerate/networks/common_utils/mobilenet_sipeed/imagenet_utils.py
axelerate/networks/common_utils/mobilenet_sipeed/mobilenet.py
axelerate/networks/segnet/__init__.py
axelerate/networks/segnet/frontend_segnet.py
axelerate/networks/segnet/metrics.py
axelerate/networks/segnet/predict.py
axelerate/networks/segnet/train.py
axelerate/networks/segnet/data_utils/__init__.py
axelerate/networks/segnet/data_utils/data_loader.py
axelerate/networks/segnet/models/__init__.py
axelerate/networks/segnet/models/_pspnet_2.py
axelerate/networks/segnet/models/all_models.py
axelerate/networks/segnet/models/basic_models.py
axelerate/networks/segnet/models/config.py
axelerate/networks/segnet/models/fcn.py
axelerate/networks/segnet/models/model.py
axelerate/networks/segnet/models/model_utils.py
axelerate/networks/segnet/models/pspnet.py
axelerate/networks/segnet/models/segnet.py
axelerate/networks/segnet/models/unet.py
axelerate/networks/yolo/__init__.py
axelerate/networks/yolo/frontend.py
axelerate/networks/yolo/backend/__init__.py
axelerate/networks/yolo/backend/batch_gen.py
axelerate/networks/yolo/backend/decoder.py
axelerate/networks/yolo/backend/loss.py
axelerate/networks/yolo/backend/network.py
axelerate/networks/yolo/backend/utils/__init__.py
axelerate/networks/yolo/backend/utils/annotation.py
axelerate-0.7.5.dist-info/LICENSE
axelerate-0.7.5.dist-info/METADATA
axelerate-0.7.5.dist-info/WHEEL
axelerate-0.7.5.dist-info/top_level.txt
axelerate-0.7.5.dist-info/RECORD
