Metadata-Version: 2.1
Name: axelerate
Version: 0.7.5
Summary: Keras-based framework for AI on the Edge
Home-page: https://github.com/AIWintermuteAI
Author: Dmitry Maslov
Author-email: dmitrywat@gmail.com
License: UNKNOWN
Platform: UNKNOWN
License-File: LICENSE
Requires-Dist: tensorflow (>=2.3.0)
Requires-Dist: imgaug (==0.4)
Requires-Dist: opencv-python (~=4.5)
Requires-Dist: matplotlib (~=3.4)
Requires-Dist: sklearn
Requires-Dist: tqdm
Requires-Dist: pascal-voc-writer
Requires-Dist: tf2onnx
